dtop/__init__.py
dtop/main.py
dtop/actions/__init__.py
dtop/actions/container_actions.py
dtop/core/__init__.py
dtop/core/docker_tui.py
dtop/core/stats.py
dtop/utils/__init__.py
dtop/utils/config.py
dtop/utils/normalize_logs.py
dtop/utils/utils.py
dtop/views/__init__.py
dtop/views/inspect_view.py
dtop/views/log_view.py
dtop-1.0.2.dist-info/licenses/LICENSE
dtop-1.0.2.dist-info/METADATA
dtop-1.0.2.dist-info/WHEEL
dtop-1.0.2.dist-info/entry_points.txt
dtop-1.0.2.dist-info/top_level.txt
dtop-1.0.2.dist-info/RECORD
