Metadata-Version: 2.4
Name: dtop
Version: 1.0.2
Summary: A high-performance terminal UI for Docker container management
Author: StakeSquid
License-Expression: MIT
Project-URL: Homepage, https://github.com/StakeSquid/dtop
Project-URL: Repository, https://github.com/StakeSquid/dtop
Project-URL: Issues, https://github.com/StakeSquid/dtop/issues
Keywords: docker,tui,terminal,containers,monitoring
Classifier: Development Status :: 5 - Production/Stable
Classifier: Environment :: Console :: Curses
Classifier: Intended Audience :: Developers
Classifier: Intended Audience :: System Administrators
Classifier: Operating System :: POSIX :: Linux
Classifier: Operating System :: MacOS
Classifier: Operating System :: Unix
Classifier: Programming Language :: Python :: 3
Classifier: Programming Language :: Python :: 3.8
Classifier: Programming Language :: Python :: 3.9
Classifier: Programming Language :: Python :: 3.10
Classifier: Programming Language :: Python :: 3.11
Classifier: Programming Language :: Python :: 3.12
Classifier: Topic :: System :: Monitoring
Classifier: Topic :: System :: Systems Administration
Classifier: Topic :: Utilities
Requires-Python: >=3.8
License-File: LICENSE
Requires-Dist: docker>=6.0.0
Provides-Extra: full
Requires-Dist: aiohttp>=3.8.0; extra == "full"
Dynamic: license-file
